module_import_checker/__init__.py
module_import_checker/cli.py
module_import_checker/module_import_checker.py
module_import_checker-0.0.13.dist-info/LICENSE
module_import_checker-0.0.13.dist-info/METADATA
module_import_checker-0.0.13.dist-info/WHEEL
module_import_checker-0.0.13.dist-info/entry_points.txt
module_import_checker-0.0.13.dist-info/top_level.txt
module_import_checker-0.0.13.dist-info/RECORD
