Metadata-Version: 2.1
Name: module-import-checker
Version: 0.0.13
Summary: An utility tool to check for inappropriate imports between modules in a Python project. and can be use to enforce modular boundaries.
Home-page: https://github.com/Abiorh001/module_import_checker.git
Author: Abiola Adeshina
Author-email: abiolaadeshinaadedayo@gmail.com
License: UNKNOWN
Platform: UNKNOWN
Classifier: Programming Language :: Python :: 3
Classifier: License :: OSI Approved :: GNU General Public License (GPL)
Classifier: Operating System :: OS Independent
License-File: LICENSE
